spiakid_simulation/Simulation.py
spiakid_simulation/__init__.py
spiakid_simulation/spiakid_simulation_par/SimPhoton.py
spiakid_simulation/spiakid_simulation_par/__init__.py
spiakid_simulation/spiakid_simulation_par/fun/Star_generation.py
spiakid_simulation/spiakid_simulation_par/fun/Calibration/Calib.py
spiakid_simulation/spiakid_simulation_par/fun/Constant/DataChecking.py
spiakid_simulation/spiakid_simulation_par/fun/Crater/CraterSpectrum.py
spiakid_simulation/spiakid_simulation_par/fun/Filter/cmplxIQ_params.py
spiakid_simulation/spiakid_simulation_par/fun/Filter/data_reading.py
spiakid_simulation/spiakid_simulation_par/fun/Filter/filter.py
spiakid_simulation/spiakid_simulation_par/fun/Filter/resonator.py
spiakid_simulation/spiakid_simulation_par/fun/PSF/turbulence.py
spiakid_simulation/spiakid_simulation_par/fun/Phase/phase_conversion.py
spiakid_simulation/spiakid_simulation_par/fun/Photon/sim_image_photon.py
spiakid_simulation/spiakid_simulation_par/fun/Rot/rot.py
spiakid_simulation/spiakid_simulation_par/fun/output/HDF5_creation.py
spiakid_simulation-1.38.6.dist-info/licenses/LICENSE
spiakid_simulation-1.38.6.dist-info/METADATA
spiakid_simulation-1.38.6.dist-info/WHEEL
spiakid_simulation-1.38.6.dist-info/top_level.txt
spiakid_simulation-1.38.6.dist-info/RECORD
