Metadata-Version: 2.4
Name: spiakid-simulation
Version: 1.38.6
Summary: Data simulation of SPIAKID project
Author-email: Sebastien Faes <faesebastien@gmail.com>
Project-URL: Homepage, https://spiakid.pages.obspm.fr/simulation/index.html
Classifier: Programming Language :: Python :: 3
Classifier: Operating System :: OS Independent
Requires-Python: <=3.11
License-File: LICENSE
Requires-Dist: numpy
Requires-Dist: matplotlib
Requires-Dist: pyyaml
Requires-Dist: astropy
Requires-Dist: scipy
Requires-Dist: lmfit
Requires-Dist: h5py
Requires-Dist: spectral_cube
Requires-Dist: ephem
Dynamic: license-file
